msauth_browser/__main__.py
msauth_browser/cli.py
msauth_browser/configs/graph.json
msauth_browser/configs/outlook.json
msauth_browser/configs/powerapps.json
msauth_browser/configs/powerautomate.json
msauth_browser/configs/teams.json
msauth_browser/core/auth.py
msauth_browser/core/config.py
msauth_browser/core/logbook.py
msauth_browser/core/tokens.py
msauth_browser-0.2.3.dist-info/METADATA
msauth_browser-0.2.3.dist-info/WHEEL
msauth_browser-0.2.3.dist-info/entry_points.txt
msauth_browser-0.2.3.dist-info/licenses/LICENSE
msauth_browser-0.2.3.dist-info/RECORD
