Metadata-Version: 2.4
Name: msauth-browser
Version: 0.2.3
Summary: 🎭 Extract Microsoft OAuth tokens using Playwright browser automation.
License: GPL-3.0-or-later
License-File: LICENSE
Author: n3rada
Author-email: 72791564+n3rada@users.noreply.github.com
Requires-Python: >=3.11,<4.0
Classifier: License :: OSI Approved :: GNU General Public License v3 or later (GPLv3+)
Classifier: Programming Language :: Python :: 3
Classifier: Programming Language :: Python :: 3.11
Classifier: Programming Language :: Python :: 3.12
Classifier: Programming Language :: Python :: 3.13
Classifier: Programming Language :: Python :: 3.14
Requires-Dist: httpx[socks] (>=0.28.1,<0.29.0)
Requires-Dist: loguru (>=0.7.3,<0.8.0)
Requires-Dist: pkce (>=1.0.3,<2.0.0)
Requires-Dist: playwright (>=1.52.0,<2.0.0)
Requires-Dist: pyperclip (>=1.11.0,<2.0.0)
Project-URL: Repository, https://github.com/n3rada/msauth-browser
